<?xml version="1.0" encoding="UTF-8"?>
<!DOCTYPE mapper PUBLIC "-//mybatis.org//DTD Mapper 3.0//EN" "http://mybatis.org/dtd/mybatis-3-mapper.dtd">
<mapper namespace="com.njit.zang.mapper.ChatNotesDao">
  <resultMap id="BaseResultMap" type="com.njit.zang.model.ChatNotes">
    <result column="from_user_id" jdbcType="VARCHAR" property="fromUserId" />
    <result column="to_user_id" jdbcType="VARCHAR" property="toUserId" />
  </resultMap>
  <sql id="Example_Where_Clause">
    <where>
      <foreach collection="oredCriteria" item="criteria" separator="or">
        <if test="criteria.valid">
          <trim prefix="(" prefixOverrides="and" suffix=")">
            <foreach collection="criteria.criteria" item="criterion">
              <choose>
                <when test="criterion.noValue">
                  and ${criterion.condition}
                </when>
                <when test="criterion.singleValue">
                  and ${criterion.condition} #{criterion.value}
                </when>
                <when test="criterion.betweenValue">
                  and ${criterion.condition} #{criterion.value} and #{criterion.secondValue}
                </when>
                <when test="criterion.listValue">
                  and ${criterion.condition}
                  <foreach close=")" collection="criterion.value" item="listItem" open="(" separator=",">
                    #{listItem}
                  </foreach>
                </when>
              </choose>
            </foreach>
          </trim>
        </if>
      </foreach>
    </where>
  </sql>
  <sql id="Update_By_Example_Where_Clause">
    <where>
      <foreach collection="example.oredCriteria" item="criteria" separator="or">
        <if test="criteria.valid">
          <trim prefix="(" prefixOverrides="and" suffix=")">
            <foreach collection="criteria.criteria" item="criterion">
              <choose>
                <when test="criterion.noValue">
                  and ${criterion.condition}
                </when>
                <when test="criterion.singleValue">
                  and ${criterion.condition} #{criterion.value}
                </when>
                <when test="criterion.betweenValue">
                  and ${criterion.condition} #{criterion.value} and #{criterion.secondValue}
                </when>
                <when test="criterion.listValue">
                  and ${criterion.condition}
                  <foreach close=")" collection="criterion.value" item="listItem" open="(" separator=",">
                    #{listItem}
                  </foreach>
                </when>
              </choose>
            </foreach>
          </trim>
        </if>
      </foreach>
    </where>
  </sql>
  <sql id="Base_Column_List">
    from_user_id, to_user_id
  </sql>
  <select id="selectByExample" parameterType="com.njit.zang.model.ChatNotesExample" resultMap="BaseResultMap">
    select
    <if test="distinct">
      distinct
    </if>
    <include refid="Base_Column_List" />
    from chat_notes
    <if test="_parameter != null">
      <include refid="Example_Where_Clause" />
    </if>
    <if test="orderByClause != null">
      order by ${orderByClause}
    </if>
    <if test="limit != null">
      <if test="offset != null">
        limit ${offset}, ${limit}
      </if>
      <if test="offset == null">
        limit ${limit}
      </if>
    </if>
  </select>
  <delete id="deleteByExample" parameterType="com.njit.zang.model.ChatNotesExample">
    delete from chat_notes
    <if test="_parameter != null">
      <include refid="Example_Where_Clause" />
    </if>
  </delete>
  <insert id="insert" parameterType="com.njit.zang.model.ChatNotes">
    insert into chat_notes (from_user_id, to_user_id)
    values (#{fromUserId,jdbcType=VARCHAR}, #{toUserId,jdbcType=VARCHAR})
  </insert>
  <insert id="insertSelective" parameterType="com.njit.zang.model.ChatNotes">
    insert into chat_notes
    <trim prefix="(" suffix=")" suffixOverrides=",">
      <if test="fromUserId != null">
        from_user_id,
      </if>
      <if test="toUserId != null">
        to_user_id,
      </if>
    </trim>
    <trim prefix="values (" suffix=")" suffixOverrides=",">
      <if test="fromUserId != null">
        #{fromUserId,jdbcType=VARCHAR},
      </if>
      <if test="toUserId != null">
        #{toUserId,jdbcType=VARCHAR},
      </if>
    </trim>
  </insert>
  <select id="countByExample" parameterType="com.njit.zang.model.ChatNotesExample" resultType="java.lang.Long">
    select count(*) from chat_notes
    <if test="_parameter != null">
      <include refid="Example_Where_Clause" />
    </if>
  </select>
  <update id="updateByExampleSelective" parameterType="map">
    update chat_notes
    <set>
      <if test="record.fromUserId != null">
        from_user_id = #{record.fromUserId,jdbcType=VARCHAR},
      </if>
      <if test="record.toUserId != null">
        to_user_id = #{record.toUserId,jdbcType=VARCHAR},
      </if>
    </set>
    <if test="_parameter != null">
      <include refid="Update_By_Example_Where_Clause" />
    </if>
  </update>
  <update id="updateByExample" parameterType="map">
    update chat_notes
    set from_user_id = #{record.fromUserId,jdbcType=VARCHAR},
      to_user_id = #{record.toUserId,jdbcType=VARCHAR}
    <if test="_parameter != null">
      <include refid="Update_By_Example_Where_Clause" />
    </if>
  </update>
</mapper>